[
  {
    "allocation": "63078.00",
    "project_count": 1,
    "programmes": {
      "HR02": "HR02"
    },
    "id": "HR",
    "area": "Civil society support",
    "sector": "Civil Society",
    "fm": "Norway Grants"
  },
  {
    "allocation": "577094.00",
    "project_count": 9,
    "programmes": {
      "HR02": "HR02"
    },
    "id": "HR",
    "area": "Funds for non-governmental organisations",
    "sector": "Civil Society",
    "fm": "EEA Grants"
  },
  {
    "allocation": "60287.00",
    "project_count": 1,
    "programmes": {
      "IN22": "IN22"
    },
    "id": "HR",
    "area": "Global fund for decent work and tripartite dialogue",
    "sector": "Decent Work and Tripartite Dialogue",
    "fm": "Norway Grants"
  },
  {
    "allocation": "118740.00",
    "project_count": 2,
    "programmes": {
      "HR03": "HR03"
    },
    "id": "HR",
    "area": "Local and regional initiatives to reduce national inequalities and to promote social inclusion",
    "sector": "Human and Social Development",
    "fm": "EEA Grants"
  },
  {
    "allocation": "100000.00",
    "project_count": 1,
    "programmes": {
      "HR02": "HR02"
    },
    "id": "HR0",
    "area": "Civil society support",
    "sector": "Civil Society",
    "fm": "Norway Grants"
  },
  {
    "allocation": "30359.00",
    "project_count": 1,
    "programmes": {
      "HR02": "HR02"
    },
    "id": "HR03",
    "area": "Civil society support",
    "sector": "Civil Society",
    "fm": "Norway Grants"
  },
  {
    "allocation": "19926.00",
    "project_count": 6,
    "programmes": {
      "HR02": "HR02"
    },
    "id": "HR031",
    "area": "Funds for non-governmental organisations",
    "sector": "Civil Society",
    "fm": "EEA Grants"
  },
  {
    "allocation": "61325.00",
    "project_count": 1,
    "programmes": {
      "HR02": "HR02"
    },
    "id": "HR035",
    "area": "Civil society support",
    "sector": "Civil Society",
    "fm": "Norway Grants"
  },
  {
    "allocation": "20032.00",
    "project_count": 2,
    "programmes": {
      "HR02": "HR02"
    },
    "id": "HR035",
    "area": "Funds for non-governmental organisations",
    "sector": "Civil Society",
    "fm": "EEA Grants"
  },
  {
    "allocation": "98686.00",
    "project_count": 5,
    "programmes": {
      "HR02": "HR02"
    },
    "id": "HR036",
    "area": "Funds for non-governmental organisations",
    "sector": "Civil Society",
    "fm": "EEA Grants"
  },
  {
    "allocation": "3741.00",
    "project_count": 1,
    "programmes": {
      "HR02": "HR02"
    },
    "id": "HR037",
    "area": "Funds for non-governmental organisations",
    "sector": "Civil Society",
    "fm": "EEA Grants"
  },
  {
    "allocation": "10593.00",
    "project_count": 1,
    "programmes": {
      "HR02": "HR02"
    },
    "id": "HR041",
    "area": "Funds for non-governmental organisations",
    "sector": "Civil Society",
    "fm": "EEA Grants"
  },
  {
    "allocation": "24161.00",
    "project_count": 2,
    "programmes": {
      "HR02": "HR02"
    },
    "id": "HR042",
    "area": "Funds for non-governmental organisations",
    "sector": "Civil Society",
    "fm": "EEA Grants"
  },
  {
    "allocation": "2469.00",
    "project_count": 1,
    "programmes": {
      "HR02": "HR02"
    },
    "id": "HR045",
    "area": "Funds for non-governmental organisations",
    "sector": "Civil Society",
    "fm": "EEA Grants"
  },
  {
    "allocation": "29855.00",
    "project_count": 1,
    "programmes": {
      "HR02": "HR02"
    },
    "id": "HR046",
    "area": "Civil society support",
    "sector": "Civil Society",
    "fm": "Norway Grants"
  },
  {
    "allocation": "8042.00",
    "project_count": 3,
    "programmes": {
      "HR02": "HR02"
    },
    "id": "HR046",
    "area": "Funds for non-governmental organisations",
    "sector": "Civil Society",
    "fm": "EEA Grants"
  },
  {
    "allocation": "7549.00",
    "project_count": 3,
    "programmes": {
      "HR02": "HR02"
    },
    "id": "HR049",
    "area": "Funds for non-governmental organisations",
    "sector": "Civil Society",
    "fm": "EEA Grants"
  },
  {
    "allocation": "64191.00",
    "project_count": 5,
    "programmes": {
      "HR02": "HR02"
    },
    "id": "HR04B",
    "area": "Funds for non-governmental organisations",
    "sector": "Civil Society",
    "fm": "EEA Grants"
  },
  {
    "allocation": "2758.00",
    "project_count": 1,
    "programmes": {
      "HR02": "HR02"
    },
    "id": "HR04C",
    "area": "Funds for non-governmental organisations",
    "sector": "Civil Society",
    "fm": "EEA Grants"
  },
  {
    "allocation": "13403.00",
    "project_count": 5,
    "programmes": {
      "HR02": "HR02"
    },
    "id": "HR04D",
    "area": "Funds for non-governmental organisations",
    "sector": "Civil Society",
    "fm": "EEA Grants"
  },
  {
    "allocation": "3165602.00",
    "project_count": 1,
    "programmes": {
      "HR04": "HR04"
    },
    "id": "HR04D",
    "area": "Judicial capacity-building and cooperation",
    "sector": "Justice and Home Affairs",
    "fm": "Norway Grants"
  },
  {
    "allocation": "9603.00",
    "project_count": 3,
    "programmes": {
      "HR02": "HR02"
    },
    "id": "HR04E",
    "area": "Funds for non-governmental organisations",
    "sector": "Civil Society",
    "fm": "EEA Grants"
  }
]